{
    "version": "0.1",
    "topology": {
      "nodes": [
        "node_A",
        "node_B",
        "node_C",
        "node_D",
        "sw_8",
        "sw_9"
      ],
      "links": [
        {"u": "node_A", "v": "sw_8", "w_uv": 1, "w_vu": 1},
        {"u": "node_B", "v": "sw_8", "w_uv": 1, "w_vu": 1},
        {"u": "node_C", "v": "sw_9", "w_uv": 1, "w_vu": 1},
        {"u": "node_D", "v": "sw_9", "w_uv": 1, "w_vu": 1},
        {"u": "sw_8", "v": "sw_9", "w_uv": 1, "w_vu": 1}
      ],
      "static_routes": [],
      "bgp": {
        "as": 1000,
        "auto": "full_mesh",
        "external_routers": [
          {
            "name": "ext_D",
            "peers_with": "node_D",
            "peer_id": 500,
            "as": 0
          }
        ]
      }
    },
    "announcements": {
        "10.0.0.0/8": {
          "ext_D": {
            "lp": 0,
            "aspl": 0,
            "origin": 0,
            "med": 0
          }
        }
      },
    "failures": {
        "type": "LinkFailureModel",
        "p_link_failure": 0.01
      },
    "properties": [{
      "type": "Reachable",
      "flow": {
        "src": "node_A",
        "dst": "10.0.0.0/8"
      }
    }]
  }
  
  
